MANIFEST.in
README.md
setup.py
pydouble/UI.py
pydouble/__init__.py
pydouble/iconapp.ico
pydouble/iconapp.png
pydouble/job.py
pydouble/pydouble.py
pydouble/test.py
pydouble.egg-info/PKG-INFO
pydouble.egg-info/SOURCES.txt
pydouble.egg-info/dependency_links.txt
pydouble.egg-info/requires.txt
pydouble.egg-info/top_level.txt