Metadata-Version: 1.1
Name: pydouble
Version: 1.4
Summary: Pydouble can find duplicated files.
Home-page: https://github.com/jhautefeuille/pydouble
Author: Julien Hautefeuille
Author-email: julien@hautefeuille.eu
License: BSD
Platform: UNKNOWN
Classifier: Programming Language :: Python
Classifier: Natural Language :: French
Classifier: Operating System :: OS Independent
Classifier: Programming Language :: Python :: 2.7
Classifier: Topic :: Utilities
